llmloader/__init__.py
llmloader/anthropic.py
llmloader/azure.py
llmloader/dummy.py
llmloader/gemini.py
llmloader/huggingface.py
llmloader/llama.py
llmloader/llama_model.py
llmloader/loader.py
llmloader/main.py
llmloader/mistral.py
llmloader/openai.py
llmloader/openrouter.py
llmloader/xai.py
llmloader-0.1.9.dist-info/METADATA
llmloader-0.1.9.dist-info/WHEEL
llmloader-0.1.9.dist-info/entry_points.txt
llmloader-0.1.9.dist-info/RECORD
