Metadata-Version: 2.3
Name: llmloader
Version: 0.1.9
Summary: Loads a Langchain LLM by model name as a string.
License: Apache-2.0
Author: Robert Turnbull
Author-email: robert.turnbull@unimelb.edu.au
Requires-Python: >=3.10,<4.0
Classifier: License :: OSI Approved :: Apache Software License
Classifier: Programming Language :: Python :: 3
Classifier: Programming Language :: Python :: 3.10
Classifier: Programming Language :: Python :: 3.11
Classifier: Programming Language :: Python :: 3.12
Classifier: Programming Language :: Python :: 3.13
Provides-Extra: llama
Requires-Dist: accelerate (>=0.31.0) ; extra == "llama"
Requires-Dist: bitsandbytes (>=0.43.1) ; extra == "llama"
Requires-Dist: langchain (>=0.2.1)
Requires-Dist: langchain-anthropic (>=0.2.4)
Requires-Dist: langchain-azure-ai (>=1.0.4,<2.0.0)
Requires-Dist: langchain-community (>=0.3.12)
Requires-Dist: langchain-google-genai (>=4.0.0,<5.0.0)
Requires-Dist: langchain-huggingface (>=0.1.2) ; extra == "llama"
Requires-Dist: langchain-mistralai (>=0.2.9)
Requires-Dist: langchain-openai (>=0.1.8)
Requires-Dist: langchain-xai (>=0.2.1)
Requires-Dist: torch (>=2.2) ; extra == "llama"
Requires-Dist: transformers (>=4.41.2) ; extra == "llama"
Requires-Dist: typer (>=0.12.3)
Project-URL: Documentation, https://github.com/rbturnbull/llmloader
Project-URL: Repository, https://github.com/rbturnbull/llmloader
